shadowexif/__init__.py
shadowexif/__main__.py
shadowexif/cli.py
shadowexif/core.py
shadowexif-1.0.0.dist-info/licenses/LICENSE
shadowexif-1.0.0.dist-info/METADATA
shadowexif-1.0.0.dist-info/WHEEL
shadowexif-1.0.0.dist-info/entry_points.txt
shadowexif-1.0.0.dist-info/top_level.txt
shadowexif-1.0.0.dist-info/RECORD
