Metadata-Version: 2.4
Name: shadowexif
Version: 1.0.0
Summary: Professional EXIF metadata removal tool for privacy and security
Home-page: https://github.com/1rhino2/shadowexif
Author: 1rhino2
Author-email: xmansussy <xmansussy@yahoo.com>
Maintainer-email: xmansussy <xmansussy@yahoo.com>
License: MIT
Project-URL: Homepage, https://github.com/xmansussy/shadowexif
Project-URL: Documentation, https://github.com/xmansussy/shadowexif#readme
Project-URL: Repository, https://github.com/xmansussy/shadowexif.git
Project-URL: Bug Reports, https://github.com/xmansussy/shadowexif/issues
Project-URL: Changelog, https://github.com/xmansussy/shadowexif/blob/main/CHANGELOG.md
Keywords: exif,metadata,privacy,security,image,photo,jpeg,png,tiff
Classifier: Development Status :: 5 - Production/Stable
Classifier: Intended Audience :: Developers
Classifier: Intended Audience :: End Users/Desktop
Classifier: License :: OSI Approved :: MIT License
Classifier: Operating System :: OS Independent
Classifier: Programming Language :: Python :: 3
Classifier: Programming Language :: Python :: 3.7
Classifier: Programming Language :: Python :: 3.8
Classifier: Programming Language :: Python :: 3.9
Classifier: Programming Language :: Python :: 3.10
Classifier: Programming Language :: Python :: 3.11
Classifier: Programming Language :: Python :: 3.12
Classifier: Programming Language :: C++
Classifier: Topic :: Multimedia :: Graphics
Classifier: Topic :: Security
Classifier: Topic :: System :: Archiving
Classifier: Topic :: Utilities
Classifier: Environment :: Console
Requires-Python: >=3.7
License-File: LICENSE
Requires-Dist: Pillow>=8.0.0
Requires-Dist: piexif>=1.1.3
Provides-Extra: dev
Requires-Dist: pytest>=6.0; extra == "dev"
Requires-Dist: pytest-cov; extra == "dev"
Requires-Dist: black; extra == "dev"
Requires-Dist: flake8; extra == "dev"
Requires-Dist: mypy; extra == "dev"
Requires-Dist: build; extra == "dev"
Requires-Dist: twine; extra == "dev"
Provides-Extra: speedup
Requires-Dist: pybind11>=2.6.0; extra == "speedup"
Dynamic: author
Dynamic: home-page
Dynamic: license-file
Dynamic: requires-python
